runusb/__init__.py
runusb/__main__.py
runusb-2025.0.0.dist-info/LICENSE
runusb-2025.0.0.dist-info/METADATA
runusb-2025.0.0.dist-info/WHEEL
runusb-2025.0.0.dist-info/entry_points.txt
runusb-2025.0.0.dist-info/top_level.txt
runusb-2025.0.0.dist-info/RECORD
