Metadata-Version: 2.1
Name: runusb
Version: 2025.0.0
Summary: Automagic running of USB sticks
Home-page: https://github.com/sourcebots/runusb
Author: "Alistair Lynn"
License: MIT
Requires-Python: >=3.8
License-File: LICENSE
Requires-Dist: logger-extras ==0.4.2
Requires-Dist: rpi.GPIO ==0.7.1
Provides-Extra: mqtt
Requires-Dist: logger-extras[mqtt] ==0.4.2 ; extra == 'mqtt'
